<?xml version="1.0" encoding="utf-8"?>
<Behaviour xmlns:xsi="http://www.w3.org/0001/XMLSchema-instance" xmlns:xsd="http://www.w3.org/0001/XMLSchema">
  <characterName>Guto</characterName>
  <interacatle>true</interacatle>
  <quest>-1</quest>
  <subQuest>0</subQuest>
  <total>0</total>
  <dismissible>false</dismissible>

  <dialogs>

    <dialog> <!-- Dialogo antes da quest -->
      <speech player="false" expression="0">
        <text></text>
      </speech>
    </dialog>
    <dialog> <!-- Dialogo antes da quest -->
      <speech player="false" expression="0">
        <text></text>
      </speech>
    </dialog>
    <dialog> <!-- Dialogo antes da quest -->
      <speech player="false" expression="0">
        <text></text>
      </speech>
    </dialog>
    <dialog> <!-- Dialogo antes da quest -->
      <speech player="false" expression="0">
        <text></text>
      </speech>
    </dialog>
    <dialog> <!-- Dialogo antes da quest -->
      <speech player="false" expression="0">
        <text></text>
      </speech>
    </dialog>

  	<dialog> <!-- Dialogo antes da quest -->
      <speech player="false" expression="0">
        <text>Leo, Parece que está avendo uma discursão sobre qual alimento possui mais água.</text>
      </speech>
    </dialog>
      
  </dialogs>

</Behaviour>
  